funx/__init__.py
funx-1.2.0.dist-info/LICENSE
funx-1.2.0.dist-info/METADATA
funx-1.2.0.dist-info/WHEEL
funx-1.2.0.dist-info/top_level.txt
funx-1.2.0.dist-info/RECORD
