Metadata-Version: 2.1
Name: funx
Version: 1.2.0
Summary: Python utility functions for cleaner, more readable code
Home-page: https://pypi.org/project/funx/
Author: Khiat Mohammed Abderrezzak
Author-email: khiat.dev@gmail.com
License: MIT
Keywords: python,utilities,helpers,functions,clean code,readable code,maintainable code,utility library,code quality,developer tools,productivity
Classifier: Programming Language :: Python :: 3
Classifier: Operating System :: OS Independent
Classifier: License :: OSI Approved :: MIT License
Requires-Python: >=3.6
License-File: LICENSE
